{
  "address": "    ",
  "capacity": null,
  "description": "This Silver / Grey colored Maruti Suzuki 800 Cat 2004 Hatchback\u00a0\u00a0is a fantastic deal at just Rs.975000. It comes with a Manual transmission system and has 64000km on the clock. This is a bargain you can't afford to miss so get in touch today. Don\u2019t forget to mention Carmudi when you contact the seller!",
  "fuel": "Petrol",
  "millage": "64,000 Km",
  "name": "Maruti Suzuki 800 2004",
  "price": "Rs. 975,000",
  "seller": "Mahesh Pathirage",
  "transmission": "Manual",
  "type": "Private seller"
}