{
  "address": "    ",
  "capacity": "1300 cc",
  "description": "2004\u00a0\u00a0NW- KE xxxx/ JEEP MODAL /center antenna /FULL OPTION AUTO/DUAL AIR BAG/ EPS /RIVERSE CAM /POWER WINDOW/DOUBLE\u00a0\u00a0POWER MIRROR /DVD\u00a0\u00a0/USB /BLUE TOOTH SETUP /THIRD OWNER /REMOTE KEY /AC /LICENCE UP TO JUNE\u00a0\u00a02019 WELL MAINTAINED HOME USED CAR\u00a0\u00a0BY A TEACHER",
  "fuel": "Petrol",
  "millage": "108,000 Km",
  "name": "Suzuki Swift  2005",
  "price": "Rs. 2,390,000",
  "seller": "Nihal",
  "transmission": "Automatic",
  "type": "Private seller"
}