{
  "address": "    ",
  "capacity": null,
  "description": "Suzuki supplies only the best quality vehicles and this car is yet another example from their impressive fleet. This Suzuki Swift\u00a0\u00a02007\u00a0\u00a0comes with a Automatic transmission system as well as other great features. With 140114km on the clock, this car is exceptional value at Rs.2350000. Please mention Carmudi when you contact the seller!",
  "fuel": "Petrol",
  "millage": "140,114 Km",
  "name": "Suzuki Swift  2006",
  "price": "Rs. 2,350,000",
  "seller": "Ranasingha",
  "transmission": "Automatic",
  "type": "Private seller"
}