{
  "address": "    ",
  "capacity": "1800 cc",
  "description": "2013 MODEL TOYOTA PRIUS 3RD GENERATION G TOURING CAB NUMBER, 1ST OWNER, BLACK COLOR HEAD LIGHT WASHERS ,ALLOY WHEELS ,3 SCOOP LIGHT 8 AIR BAGS ,PUSH START SMART KEY DUEL MULTIFUNCTION , LEATHER ELECTRIC SEATS ,REAR WIPER ,TV DVD REVERSE CAMERA , BRAND NEW TYRES, 100% ORIGINAL CONDITION",
  "fuel": "Hybrid Petrol",
  "millage": "70,000 Km",
  "name": "Toyota Prius  2013",
  "price": "Rs. 4,975,000",
  "seller": "Ashraff Siddique",
  "transmission": "Automatic",
  "type": "Private seller"
}