{
  "address": "    ",
  "capacity": "1500 cc",
  "description": "Personally imported through Laugh as zero mileage vehicle. Warranty 6M available. All documents including auction sheet and services data available.\u00a0\u00a0Manufacturer year 2015 December.\u00a0\u00a0Registered in 2017 January. Full options.\u00a0\u00a0Pearl white ,",
  "fuel": "Hybrid Petrol",
  "millage": "16,000 Km",
  "name": "Toyota Axio G Grade  2015",
  "price": "Rs. 5,875,000",
  "seller": "Milinda",
  "transmission": "Automatic",
  "type": "Private seller"
}