{
  "address": "    ",
  "capacity": "660 cc",
  "description": "Suzuki has delivered quality for years and this car is no exception. This new Suzuki WagonR FX 2018 Safety is available for sale and has a Automatic transmission system as well as other great features. Priced at Rs.3150000, this car is fantastic value for money. Don\u2019t forget to mention Carmudi when you contact the seller!",
  "fuel": "Hybrid",
  "millage": null,
  "name": "Suzuki WagonR FX 2018",
  "price": "Rs. 3,100,000",
  "seller": "Thushara",
  "transmission": "Automatic",
  "type": "Private seller"
}