{
  "address": "    ",
  "capacity": "1000 cc",
  "description": "Geely supplies only the best quality vehicles and this car is yet another example from their impressive fleet. This new Geely Panda panda\u00a0\u00a02018 GL comes with a Manual transmission system and is exceptional value at Rs.1095000. Don't miss this fantastic opportunity. Please remember to mention Carmudi when you contact the seller!...",
  "fuel": "Petrol",
  "millage": null,
  "name": "Geely Panda  2018",
  "price": "Rs. 1,095,000",
  "seller": "Lakmal",
  "transmission": "Manual",
  "type": "Private seller"
}